{
  "rights": [
    {
      "id": 1,
      "grade": 1,
      "key": "/home",
      "pagepermisson": true,
      "title": "首页"
    },
    {
      "id": 2,
      "grade": 1,
      "key": "/user-manage",
      "pagepermisson": true,
      "title": "用户管理"
    },
    {
      "id": 7,
      "grade": 1,
      "key": "/right-manage",
      "pagepermisson": true,
      "title": "权限管理"
    },
    {
      "id": 14,
      "grade": 1,
      "key": "/news-manage",
      "pagepermisson": true,
      "title": "新闻管理"
    },
    {
      "id": 21,
      "grade": 1,
      "key": "/audit-manage",
      "pagepermisson": true,
      "title": "审核管理"
    },
    {
      "id": 24,
      "grade": 1,
      "key": "/publish-manage",
      "pagepermisson": true,
      "title": "发布管理"
    }
  ],
  "children": [
    {
      "id": 3,
      "title": "添加用户",
      "rightId": 2,
      "key": "/user-manage/add",
      "grade": 2
    },
    {
      "id": 4,
      "title": "删除用户",
      "rightId": 2,
      "key": "/user-manage/delete",
      "grade": 2
    },
    {
      "id": 5,
      "title": "修改用户",
      "rightId": 2,
      "key": "/user-manage/update",
      "grade": 2
    },
    {
      "id": 6,
      "title": "用户列表",
      "rightId": 2,
      "key": "/user-manage/list",
      "pagepermisson": true,
      "grade": 2
    },
    {
      "id": 8,
      "title": "角色列表",
      "rightId": 7,
      "key": "/right-manage/role/list",
      "pagepermisson": true,
      "grade": 2
    },
    {
      "id": 9,
      "title": "权限列表",
      "rightId": 7,
      "key": "/right-manage/right/list",
      "pagepermisson": true,
      "grade": 2
    },
    {
      "id": 10,
      "title": "修改角色",
      "rightId": 7,
      "key": "/user-manage/role/update",
      "grade": 2
    },
    {
      "id": 11,
      "title": "删除角色",
      "rightId": 7,
      "key": "/user-manage/role/delete",
      "grade": 2
    },
    {
      "id": 12,
      "title": "修改权限",
      "rightId": 7,
      "key": "/right-manage/update",
      "grade": 2
    },
    {
      "id": 13,
      "title": "删除权限",
      "rightId": 7,
      "key": "/right-manage/delete",
      "grade": 2
    },
    {
      "id": 15,
      "title": "新闻列表",
      "rightId": 14,
      "key": "/news-manage/list",
      "grade": 2
    },
    {
      "id": 16,
      "title": "撰写新闻",
      "rightId": 14,
      "key": "/news-manage/add",
      "pagepermisson": true,
      "grade": 2
    },
    {
      "id": 17,
      "title": "新闻更新",
      "rightId": 14,
      "key": "/news-manage/update",
      "grade": 2
    },
    {
      "id": 18,
      "title": "新闻预览",
      "rightId": 14,
      "key": "/news-manage/preview",
      "grade": 2
    },
    {
      "id": 19,
      "title": "草稿箱",
      "rightId": 14,
      "key": "/news-manage/delete",
      "pagepermisson": true,
      "grade": 2
    },
    {
      "id": 20,
      "title": "新闻分类",
      "rightId": 14,
      "key": "/news-manage/classify",
      "pagepermisson": true,
      "grade": 2
    },
    {
      "id": 22,
      "title": "审核新闻",
      "rightId": 21,
      "key": "/audit-manage/news",
      "pagepermisson": true,
      "grade": 2
    },
    {
      "id": 23,
      "title": "审核列表",
      "rightId": 21,
      "key": "/audit-manage/list",
      "pagepermisson": true,
      "grade": 2
    },
    {
      "id": 25,
      "title": "待发布",
      "rightId": 24,
      "key": "/publish-manage/stay",
      "pagepermisson": true,
      "grade": 2
    },
    {
      "id": 26,
      "title": "已发布",
      "rightId": 24,
      "key": "/publish-manage/already",
      "pagepermisson": true,
      "grade": 2
    },
    {
      "id": 27,
      "title": "已下载",
      "rightId": 24,
      "key": "/publish-manage/downloaded",
      "pagepermisson": true,
      "grade": 2
    }
  ],
  "roles": [
    {
      "id": 1,
      "roleName": "超级管理员",
      "roleType": 1,
      "rights": [
        "/user-manage/add",
        "/user-manage/delete",
        "/user-manage/update",
        "/user-manage/list",
        "/right-manage/role/add",
        "/right-manage/right/list",
        "/right-manage/role/update",
        "/right-manage/role/delete",
        "/news-manage",
        "/news-manage/list",
        "/news-manage/add",
        "/news-manage/update/:id",
        "/news-manage/preview/:id",
        "/news-manage/draft",
        "/news-manage/category",
        "/audit-manage",
        "/audit-manage/audit",
        "/audit-manage/list",
        "/publish-manage",
        "/publish-manage/unpublished",
        "/publish-manage/published",
        "/publish-manage/sunset",
        "/right-manage",
        "/home",
        "/user-manage"
      ]
    },
    {
      "id": 2,
      "roleName": "区域管理员",
      "roleType": 2,
      "rights": [
        "/user-manage",
        "/user-manage/add",
        "/user-manage/delete",
        "/user-manage/update",
        "/user-manage/list",
        "/news-manage",
        "/news-manage/list",
        "/news-manage/add",
        "/news-manage/update/:id",
        "/news-manage/preview/:id",
        "/news-manage/draft",
        "/news-manage/category",
        "/audit-manage",
        "/audit-manage/audit",
        "/audit-manage/list",
        "/publish-manage",
        "/publish-manage/unpublished",
        "/publish-manage/published",
        "/publish-manage/sunset",
        "/home"
      ]
    },
    {
      "id": 3,
      "roleName": "区域编辑",
      "roleType": 3,
      "rights": [
        "/news-manage",
        "/news-manage/list",
        "/news-manage/add",
        "/news-manage/update/:id",
        "/news-manage/preview/:id",
        "/news-manage/draft",
        "/audit-manage",
        "/audit-manage/list",
        "/publish-manage",
        "/publish-manage/unpublished",
        "/publish-manage/published",
        "/publish-manage/sunset",
        "/home"
      ]
    }
  ],
  "users": [
    {
      "id": 1,
      "username": "admin",
      "password": "123456",
      "roleState": true,
      "default": true,
      "region": "",
      "roleId": 1
    },
    {
      "id": 2,
      "username": "金",
      "password": "123",
      "roleState": false,
      "default": false,
      "region": "亚洲",
      "roleId": 2
    },
    {
      "id": 3,
      "username": "木",
      "password": "123",
      "roleState": true,
      "default": false,
      "region": "南极洲",
      "roleId": 2
    },
    {
      "id": 4,
      "username": "水",
      "password": "123",
      "roleState": true,
      "default": false,
      "region": "",
      "roleId": 1
    },
    {
      "id": 5,
      "username": "火",
      "password": "123",
      "roleState": true,
      "default": false,
      "region": "南极洲",
      "roleId": 2
    }
  ]
}